Shrike FI_full_adder_project/full_adder/ffpga/src/full_adder.v
(* top *) module full_adder(
  (* iopad_external_pin *) input  a,
  (* iopad_external_pin *) input  b,
  (* iopad_external_pin *) input  c_in,
  (* iopad_external_pin *) output sum,
  (* iopad_external_pin *) output sum_en,
  (* iopad_external_pin *) output carry,
  (* iopad_external_pin *) output carry_en
  );


  assign sum_en = 1'b1;
  assign carry_en = 1'b1;
  
  assign sum = a ^ b ^ c_in;
  assign carry = (a&b) | (a&c_in) | (b&c_in);
endmodule

Shrike FI_full_adder_project/full_adder/ffpga/sim/full_test_tb.vt
// Custom testbench

`timescale 1ns / 1ps

module full_test_tb;

    reg a;
    reg b;
    reg c_in;

    wire sum;
    wire carry;
    
    wire sum_en;
    wire carry_en;

    // Instantiate the Full Adder
    full_adder uut (
        .a(a),
        .b(b),
        .c_in(c_in),
        .sum(sum),
        .sum_en(sum_en),
        .carry(carry),
        .carry_en(carry_en)
    );

    // Test all possible input combinations
    initial begin
    
    $dumpfile ("full_test_tb.vcd");
    $dumpvars (0, full_test_tb);

        $monitor("Time=%0t | a=%b b=%b c_in=%b | sum=%b carry=%b",
                 $time, a, b, c_in, sum, carry);

        a = 0; b = 0; c_in = 0; #10;
        a = 0; b = 0; c_in = 1; #10;
        a = 0; b = 1; c_in = 0; #10;
        a = 0; b = 1; c_in = 1; #10;
        a = 1; b = 0; c_in = 0; #10;
        a = 1; b = 0; c_in = 1; #10;
        a = 1; b = 1; c_in = 0; #10;
        a = 1; b = 1; c_in = 1; #10;

    $finish;
    end


endmodule

Shrike FI_full_adder_project/full_adder/ffpga/build/simulation/full_test_tb.vcd
$date
	Tue Aug 18 15:01:13 2026
$end
$version
	Icarus Verilog
$end
$timescale
	1ps
$end
$scope module full_test_tb $end
$var wire 1 ! carry_en $end
$var wire 1 " sum_en $end
$var wire 1 # sum $end
$var wire 1 $ carry $end
$var reg 1 % a $end
$var reg 1 & b $end
$var reg 1 ' c_in $end
$scope module uut $end
$var wire 1 % a $end
$var wire 1 & b $end
$var wire 1 ' c_in $end
$var wire 1 $ carry $end
$var wire 1 ! carry_en $end
$var wire 1 # sum $end
$var wire 1 " sum_en $end
$upscope $end
$upscope $end
$enddefinitions $end
$comment Show the parameter values. $end
$dumpall
$end
#0
$dumpvars
0'
0&
0%
0$
0#
1"
1!
$end
#10000
1#
1'
#20000
0'
1&
#30000
1$
0#
1'
#40000
0$
1#
0'
0&
1%
#50000
1$
0#
1'
#60000
0'
1&
#70000
1#
1'
